core/__init__.py
core/config.py
core/models/__init__.py
core/models/dataframe.py
core/models/dataset.py
core/models/dataset_meta.py
local_sdk/__init__.py
local_sdk/dataframe.py
local_sdk/faird.py
parser/__init__.py
parser/abstract_parser.py
parser/csv_parser.py
parser/nc_parser.py
parser/tif_parser.py
parser/tiff_arrow_tiff.py
sdk/__init__.py
sdk/connection.py
sdk/dacp_client.py
sdk/dataframe.py
utils/__init__.py
utils/format_utils.py
faird_local-1.0.14.dist-info/METADATA
faird_local-1.0.14.dist-info/WHEEL
faird_local-1.0.14.dist-info/top_level.txt
faird_local-1.0.14.dist-info/RECORD
