Metadata-Version: 2.1
Name: faird-local
Version: 1.0.14
Summary: A local SDK for working with DataFrame
Author: rdcn
Author-email: rdcn@cnic.com
Classifier: Programming Language :: Python :: 3
Classifier: License :: OSI Approved :: MIT License
Classifier: Operating System :: OS Independent
Requires-Python: >=3.9
Requires-Dist: pyarrow ==19.0.0
Requires-Dist: tabulate
Requires-Dist: pandas
Requires-Dist: netCDF4
Requires-Dist: rasterio
